.gitignore
.travis.yml
LICENSE
MANIFEST.in
README.rst
setup.py
tox.ini
docassemblekvsession/__init__.py
docassemblekvsession.egg-info/PKG-INFO
docassemblekvsession.egg-info/SOURCES.txt
docassemblekvsession.egg-info/dependency_links.txt
docassemblekvsession.egg-info/not-zip-safe
docassemblekvsession.egg-info/requires.txt
docassemblekvsession.egg-info/top_level.txt
docs/Makefile
docs/conf.py
docs/index.rst
docs/make.bat
docs/_static/flask_kvsession.png
docs/_themes/flask_theme_support.py
docs/_themes/flask/layout.html
docs/_themes/flask/relations.html
docs/_themes/flask/theme.conf
docs/_themes/flask/static/flasky.css_t
docs/_themes/flask_small/layout.html
docs/_themes/flask_small/theme.conf
docs/_themes/flask_small/static/flasky.css_t
logo/1299375751.svg
logo/logo.svg
tests/conftest.py
tests/test_cookieflags.py
tests/test_delayed_init.py
tests/test_expiration.py
tests/test_flask_kvsession.py
tests/test_github_issues.py
tests/test_sessionid.py