Metadata-Version: 2.1
Name: docassemblekvsession
Version: 0.9
Summary: Transparent server-side session support for flask
Home-page: https://github.com/jhpyle/flask-kvsession
Author: Marc Brinkmann and Jonathan Pyle
Author-email: jhpyle@gmail.com
License: MIT
Platform: any
Classifier: Programming Language :: Python :: 2
Classifier: Programming Language :: Python :: 3
License-File: LICENSE
